odoo/addons/invader_payment_stripe/README.rst
odoo/addons/invader_payment_stripe/__init__.py
odoo/addons/invader_payment_stripe/__manifest__.py
odoo/addons/invader_payment_stripe/demo/payment_demo.xml
odoo/addons/invader_payment_stripe/i18n/fr.po
odoo/addons/invader_payment_stripe/i18n/invader_payment_stripe.pot
odoo/addons/invader_payment_stripe/models/__init__.py
odoo/addons/invader_payment_stripe/models/payment.py
odoo/addons/invader_payment_stripe/readme/CONTRIBUTORS.rst
odoo/addons/invader_payment_stripe/readme/DESCRIPTION.rst
odoo/addons/invader_payment_stripe/services/__init__.py
odoo/addons/invader_payment_stripe/services/payment_stripe.py
odoo/addons/invader_payment_stripe/static/description/icon.png
odoo/addons/invader_payment_stripe/static/description/index.html
odoo12_addon_invader_payment_stripe-12.0.3.0.1.dist-info/METADATA
odoo12_addon_invader_payment_stripe-12.0.3.0.1.dist-info/WHEEL
odoo12_addon_invader_payment_stripe-12.0.3.0.1.dist-info/top_level.txt
odoo12_addon_invader_payment_stripe-12.0.3.0.1.dist-info/RECORD
