Metadata-Version: 2.1
Name: odoo12-addon-invader-payment-stripe
Version: 12.0.3.0.1
Summary: REST Services for Stripe Payments (base module)
Home-page: https://github.com/shopinvader/odoo-shopinvader-payment
Author: ACSONE SA/NV
License: AGPL-3
Platform: UNKNOWN
Classifier: Programming Language :: Python
Classifier: Framework :: Odoo
Classifier: Framework :: Odoo :: 12.0
Classifier: License :: OSI Approved :: GNU Affero General Public License v3
Requires-Python: >=3.5
Requires-Dist: cerberus
Requires-Dist: odoo12-addon-base-rest
Requires-Dist: odoo12-addon-invader-payment
Requires-Dist: odoo (<12.1dev,>=12.0a)
Requires-Dist: stripe
